cast_planet/__init__.py
cast_planet/exceptions.py
cast_planet/_utils/__init__.py
cast_planet/_utils/_base_api.py
cast_planet/_utils/_functions.py
cast_planet/_utils/_session_factory.py
cast_planet/basemap/__init__.py
cast_planet/basemap/aoi_search.py
cast_planet/basemap/api.py
cast_planet/basemap/models.py
cast_planet/data/__init__.py
cast_planet/data/api.py
cast_planet/data/models.py
cast_planet/data/filters/__init__.py
cast_planet/data/filters/asset.py
cast_planet/data/filters/base.py
cast_planet/data/filters/field.py
cast_planet/data/filters/logical.py
cast_planet/data/filters/permission.py
cast_planet/orders/__init__.py
cast_planet/orders/api.py
cast_planet/orders/models/__init__.py
cast_planet/orders/models/common.py
cast_planet/orders/models/order_delivery.py
cast_planet/orders/models/order_details.py
cast_planet/orders/models/order_hosting.py
cast_planet/orders/models/order_new.py
cast_planet/orders/models/order_notifications.py
cast_planet/orders/models/order_products.py
cast_planet/orders/models/orders_list.py
cast_planet/orders/models/orders_stats.py
cast_planet/orders/models/tools.py
tests/__init__.py
tests/test_basemap_aoi_search.py
tests/test_basemap_api.py
tests/test_basemap_tools.py
tests/test_data_api.py
tests/test_filters.py
tests/test_imports.py
tests/test_orders_api.py
tests/test_session_factory.py
tests/test_utils_base_api.py
tests/test_utils_functions.py
tests/mocks/__init__.py
tests/mocks/mock_logger.py
tests/mocks/mock_response.py
tests/mocks/mock_session.py
cast_planet_api-0.1.3.dist-info/METADATA
cast_planet_api-0.1.3.dist-info/WHEEL
cast_planet_api-0.1.3.dist-info/top_level.txt
cast_planet_api-0.1.3.dist-info/RECORD
